CHANGES.rst
MANIFEST.in
README.rst
VERSION.txt
setup.cfg
setup.py
adsorb/__init__.py
adsorb/adsorb.py
adsorb/test_adsorb.py
adsorb.egg-info/PKG-INFO
adsorb.egg-info/SOURCES.txt
adsorb.egg-info/dependency_links.txt
adsorb.egg-info/top_level.txt
adsorb.egg-info/zip-safe