Metadata-Version: 1.0
Name: adsorb
Version: 0.1
Summary: Lightweight loose coupling library for Python. Add listeners to a named event and call them from anywhere to collect their responses.
Home-page: http://jace.github.com/adsorb/
Author: Kiran Jonnalagadda
Author-email: jace@pobox.com
License: UNKNOWN
Keywords: event loose-coupling signal
Platform: UNKNOWN
Classifier: Programming Language :: Python
Classifier: License :: OSI Approved :: BSD License
Classifier: Operating System :: OS Independent
Classifier: Development Status :: 3 - Alpha
Classifier: Intended Audience :: Developers
Classifier: Topic :: Software Development :: Libraries :: Python Modules
